{
  "title": "Main 2",
  "link": "https://saraelshawa.com/?ct_template=main-2",
  "pub_date": "Thu, 10 Sep 2020 23:33:46 +0000",
  "post_name": "main-2",
  "post_type": "ct_template",
  "content": null,
  "meta": {
    "_edit_last": "2",
    "ct_parent_template": "10",
    "ct_template_archive_post_types_all": null,
    "ct_template_categories": "a:0:{}",
    "ct_template_categories_all": null,
    "ct_template_tags": "a:0:{}",
    "ct_template_tags_all": null,
    "ct_template_custom_taxonomies": "a:0:{}",
    "ct_template_custom_taxonomies_all": null,
    "ct_template_authors_archives_all": null,
    "ct_template_index": null,
    "ct_template_front_page": null,
    "ct_template_blog_posts": null,
    "ct_template_date_archive": null,
    "ct_template_search_page": null,
    "ct_template_inner_content": null,
    "ct_template_404_page": null,
    "ct_template_all_archives": null,
    "ct_template_archive_among_taxonomies": "a:0:{}",
    "ct_template_apply_if_archive_among_taxonomies": null,
    "ct_template_archive_post_types": "a:0:{}",
    "ct_template_apply_if_archive_among_cpt": null,
    "ct_template_authors_archives": "a:0:{}",
    "ct_template_apply_if_archive_among_authors": null,
    "ct_template_single_all": null,
    "ct_template_post_types": "a:0:{}",
    "ct_template_exclude_ids": null,
    "ct_template_include_ids": null,
    "ct_template_taxonomies": "a:2:{s:5:\"names\";a:0:{}s:6:\"values\";a:0:{}}",
    "ct_use_template_taxonomies": null,
    "ct_template_post_of_parents": "a:1:{i:0;s:0:\"\";}",
    "ct_template_apply_if_post_of_parents": null,
    "ct_template_order": "0",
    "ct_builder_shortcodes": null
  }
}